{"BookGroups":[{"UniqueId":"F16","Title":"F16書架","Subtitle":"F16操作指南，F16應急手冊，F16飛行指南","ImagePath":"ms-appx:///Assets/SmallTile.scale-400.png","Description":"F16操作指南，F16應急手冊。。。。。。","Items":[{"UniqueId":"USAF-F16s-a","Title":"F16操作指南","Subtitle":"F16操作指南","ImagePath":"ms-appx:///Assets/F16-User-manual.png","Description":"WARNING: This document contains technical data whose export is restricted by the Arms Export Control","BookPath":"ms-appx:///Data/USAF-F16s.pdf"},{"UniqueId":"USAF-F16s-b","Title":"F16應急手冊","Subtitle":"F16應急手冊","ImagePath":"ms-appx:///Assets/F16-User-manual.png","Description":"WARNING: This document contains technical data whose export is restricted by the Arms Export Control","BookPath":"ms-appx:///Data/USAF-F16s.pdf"},{"UniqueId":"USAF-F16s-c","Title":"F16飛行指南","Subtitle":"F16飛行指南","ImagePath":"ms-appx:///Assets/F16-User-manual.png","Description":"WARNING: This document contains technical data whose export is restricted by the Arms Export Control","BookPath":"ms-appdata:///local/Data/ST.pdf"},{"UniqueId":"USAF-F16s-d","Title":"測試","Subtitle":"F16飛行指南","ImagePath":"ms-appx:///Assets/F16-User-manual.png","Description":"WARNING: This document contains technical data whose export is restricted by the Arms Export Control","BookPath":"ms-appdata:///local/Data/ST.pdf"}]}]}